pix2vec/__init__.py
pix2vec/cli.py
pix2vec/pix2vec.py
pix2vec-0.1.5.dist-info/AUTHORS.rst
pix2vec-0.1.5.dist-info/LICENSE
pix2vec-0.1.5.dist-info/METADATA
pix2vec-0.1.5.dist-info/WHEEL
pix2vec-0.1.5.dist-info/entry_points.txt
pix2vec-0.1.5.dist-info/top_level.txt
pix2vec-0.1.5.dist-info/RECORD
