Metadata-Version: 2.1
Name: pix2vec
Version: 0.1.5
Summary: pix2vec produces a vector representation of planetary mapping spectrometers hyperspectral and camera ISIS data cube
Home-page: https://github.com/afrigeri/pix2vec
Author: Alessandro Frigeri
Author-email: alessandro.frigeri@inaf.it
License: GNU General Public License v3
Keywords: pix2vec
Classifier: Development Status :: 2 - Pre-Alpha
Classifier: Intended Audience :: Science/Research
Classifier: Intended Audience :: Developers
Classifier: Intended Audience :: End Users/Desktop
Classifier: License :: OSI Approved :: GNU General Public License v3 (GPLv3)
Classifier: Natural Language :: English
Classifier: Programming Language :: Python :: 3
Classifier: Programming Language :: Python :: 3.6
Classifier: Programming Language :: Python :: 3.7
Classifier: Programming Language :: Python :: 3.8
Requires-Python: >=3.6
License-File: LICENSE
License-File: AUTHORS.rst
